{
  "type": "FeatureCollection",
  "generator": "overpass-ide",
  "copyright": "The data included in this document is from www.openstreetmap.org. The data is made available under ODbL.",
  "timestamp": "2022-04-26T01:00:26Z",
  "features": [
    {
      "type": "Feature",
      "properties": {
        "@id": "node/2519231198",
        "leisure": "park",
        "name": "Palacio da Cristal"
      },
      "geometry": {
        "type": "Point",
        "coordinates": [
          -8.6266132,
          41.146922
        ]
      },
      "id": "node/2519231198"
    }
  ]
}